{
    "스타벅스 구로디지털로점": [
        "친절하고 분위기 좋습니다!!\n직원분이 친절하셔서 기분이 좋아지더라구요😀 ",
        "직원이 너무 불친절해요; ",
        "여기 어떤여자분 알바생 불친절.. 일요일6시 되면 나가라고 정색하면서..  "
    ],
    "스타벅스 구로에이스점": [
        "월요일 오전은 참 한가해서 좋다. ",
        "매장분위기도 좋고 직원들도 친절한대…\n커피는 담뱃재에 물 탄것 마냥 너무 너무 놀랐네요 ...\n모처럼 오랜만에 충격적인 커피 마셨네요 … 😭😭😭 ",
        "여기 아메리카노는 알바생이 문제인지 원두보관이 문제인지 진찌 탄맛이 미첫음.. 노브랜드 커피가 훨 맛잇음.. 아메리카노빼고 다른건 맛잇음 "
    ],
    "스타벅스 구로디지털타워점": [
        "와이파이가 너무 안잡혔읍니다... ",
        "기분 좋게 커피 마실수있어서 행복하네여! 직원분들이  친절하세요!! ",
        "다른건 다 좋은데 페미가 많네요 "
    ],
    "스타벅스 구로구청점": [
        "+와이파이 겁나 끊깁니다 참고하세요;; 서울시 와이파이도 잡히긴 하는데 아무튼 빠른 와이파이 필요한 작업 하려면 비추입니다\n\n엄청 넓고 내부 자리 많아요 테이블이랑 좌석도 다양하게 구성되어 있어서 취향껏 편하게 앉을 수 있고 직원 분들 친절하심 접기",
        "파트너들이 친절합니다 건물 화장실이 너무 냄새나는거빼곤 매장은 만족스럽습니다 ",
        "버리기 아까운 컵홀더.. 넘 귀여워요  ",
        "앉아서 공부하기 괜찮고 좌석도 여유롭습니다 ",
        "e모바일 쿠폰 교환하러 갔는데 원하는 카드를 선택하게 하지 않고 아무거나 해주라는 매니저(?).. 내가 나이먹은 사람이라 그런가 하는 느낌을 받았는데 그리 기분이 좋지않네요. ",
        "친절해요 ",
        "인터넷 작업 필요하면 다른 데 ㅊㅊ\n오해 없길 직원 친절함\n\n와이파이... 더보기",
        "스벅 자체는 괜찮은데, 건물 화장실이 겁나 별로... 화장실 출입구 안에 남/여 화장실이 나뉘었는데 문은 없어서 남자든 여자든 서로 싸는 거 다 볼 수 있음;;; ",
        "가끔가는 구로구청 고대병원후문 스타벅스\n주문받는 서비스가 항상무시하는 … 마인드 ",
        "좋았습니다!!생긴지 얼마안되서 체공체고! "
    ],
    "스타벅스 구로하이엔드점": [
        "매장이 항싱 깨끗하고\n직원들도 매우매우 친절함\n평일 점심에는 사람 진짜 많은데 오후에는 여유롭고 조용해서 업무처리하기 굿둣 ",
        "직원들이 불친절해서 조금 멀더라도 다른 지점 이용합니다. ",
        "회사에서 가까워서 가끔 이용하는 곳인데 항상 갈때마다 다른 스벅에 비해 사람이 별로 없어서 주문이 매우 빨리 나오는 장점이 있습니다. 다만 직원들이 전체적으로 불친절한 지점같습니... 더보기",
        "갑자기 사라졌네요. 폐업인지...사람이 좀 없기는 했음 ",
        "근처 다른 스벅에 비해 문을 일찍 닫는게 아쉽지만 무난합니다. ",
        "무난 "
    ]
}